rest_framework_mvt/__init__.py
rest_framework_mvt/managers.py
rest_framework_mvt/renderers.py
rest_framework_mvt/schemas.py
rest_framework_mvt/views.py
djangorestframework_mvt-0.2.4.dist-info/LICENSE.txt
djangorestframework_mvt-0.2.4.dist-info/METADATA
djangorestframework_mvt-0.2.4.dist-info/WHEEL
djangorestframework_mvt-0.2.4.dist-info/top_level.txt
djangorestframework_mvt-0.2.4.dist-info/RECORD
