Metadata-Version: 2.1
Name: djangorestframework-mvt
Version: 0.2.4
Summary:         A Django REST Framework extension for creating views that serialize model data to Google Protobuf encoded Map Box Vector Tiles via Postgres.
Home-page: https://github.com/corteva/djangorestframework-mvt
Author: Corteva Data Engineering
Author-email: DL-Delta-Devs@corteva.com
License: UNKNOWN
Keywords: mvt,django,restframework,mapbox,vector,protobuf,tile,postgres
Platform: UNKNOWN
Classifier: Framework :: Django
Classifier: Intended Audience :: Developers
Classifier: Intended Audience :: Science/Research
Classifier: License :: OSI Approved :: BSD License
Classifier: Natural Language :: English
Classifier: Operating System :: POSIX :: Linux
Classifier: Operating System :: MacOS
Classifier: Operating System :: Microsoft :: Windows
Classifier: Programming Language :: Python :: 3 :: Only
Classifier: Topic :: Database
Classifier: Topic :: Scientific/Engineering :: GIS
Requires-Dist: coreapi (>=2.3)
Requires-Dist: django (>=2.2.9)
Requires-Dist: djangorestframework (>=3.9)
Requires-Dist: djangorestframework-gis (>=0.14)
Requires-Dist: django-filter (>=2.1.0)
Provides-Extra: dev
Requires-Dist: black ; extra == 'dev'
Requires-Dist: coveralls ; extra == 'dev'
Requires-Dist: mock ; extra == 'dev'
Requires-Dist: pylint ; extra == 'dev'
Requires-Dist: pytest ; extra == 'dev'
Requires-Dist: pytest-cov ; extra == 'dev'
Requires-Dist: sphinx ; extra == 'dev'
Requires-Dist: sphinx-rtd-theme ; extra == 'dev'
